<?xml version="1.0" encoding="UTF-8"?>
<sbml xmlns="http://www.sbml.org/sbml/level3/version1/core" level="3" version="1">
  <model id="example_model" name="Example Inconsistent Model">
    <listOfCompartments>
      <compartment id="c" name="Cytosol" spatialDimensions="3" size="1" constant="true"/>
    </listOfCompartments>
    <listOfSpecies>
      <species id="M_A_c" name="A" compartment="c" hasOnlySubstanceUnits="false" boundaryCondition="false" constant="false"/>
      <species id="M_B_c" name="B" compartment="c" hasOnlySubstanceUnits="false" boundaryCondition="false" constant="false"/>
      <species id="M_C_c" name="C" compartment="c" hasOnlySubstanceUnits="false" boundaryCondition="false" constant="false"/>
      <species id="M_D_c" name="D" compartment="c" hasOnlySubstanceUnits="false" boundaryCondition="false" constant="false"/>
    </listOfSpecies>
    <listOfReactions>
      <reaction id="R_xx1" reversible="true" fast="false">
        <listOfReactants>
          <speciesReference species="M_A_c" stoichiometry="1" constant="true"/>
        </listOfReactants>
        <listOfProducts>
          <speciesReference species="M_B_c" stoichiometry="1" constant="true"/>
          <speciesReference species="M_C_c" stoichiometry="1" constant="true"/>
        </listOfProducts>
      </reaction>
      <reaction id="R_xx22" reversible="true" fast="false">
        <listOfReactants>
          <speciesReference species="M_A_c" stoichiometry="1" constant="true"/>
        </listOfReactants>
        <listOfProducts>
          <speciesReference species="M_B_c" stoichiometry="1" constant="true"/>
        </listOfProducts>
      </reaction>
      <reaction id="R_xx3" reversible="true" fast="false">
        <listOfReactants>
          <speciesReference species="M_C_c" stoichiometry="1" constant="true"/>
        </listOfReactants>
        <listOfProducts>
          <speciesReference species="M_D_c" stoichiometry="1" constant="true"/>
        </listOfProducts>
      </reaction>
    </listOfReactions>
  </model>
</sbml>